dbrownell_VSCodeTools/VSCodeCogger/CogTools/PopulateTests.py
dbrownell_VSCodeTools/VSCodeCogger/CogTools/__init__.py
dbrownell_VSCodeTools/VSCodeCogger/__init__.py
dbrownell_VSCodeTools/VSCodeCogger/__main__.py
dbrownell_VSCodeTools/__init__.py
dbrownell_VSCodeTools/py.typed
dbrownell_vscodetools-0.2.0.dist-info/WHEEL
dbrownell_vscodetools-0.2.0.dist-info/entry_points.txt
dbrownell_vscodetools-0.2.0.dist-info/METADATA
dbrownell_vscodetools-0.2.0.dist-info/RECORD
