Metadata-Version: 2.3
Name: dbrownell-vscodetools
Version: 0.2.0
Summary: Tools used when working with VSCode.
Author: David Brownell
Author-email: David Brownell <github@davidbrownell.com>
License: MIT
Classifier: Operating System :: MacOS
Classifier: Operating System :: Microsoft :: Windows
Classifier: Operating System :: POSIX :: Linux
Classifier: Programming Language :: Python
Classifier: Programming Language :: Python :: 3.14
Requires-Dist: cogapp>=3.6.0
Requires-Dist: dbrownell-common>=0.16.0
Requires-Dist: typer>=0.20.1
Requires-Python: >=3.14
Project-URL: Documentation, https://github.com/davidbrownell/dbrownell_VSCodeTools
Project-URL: Homepage, https://github.com/davidbrownell/dbrownell_VSCodeTools
Project-URL: Repository, https://github.com/davidbrownell/dbrownell_VSCodeTools
